adafruit_ds1307.py
adafruit_circuitpython_ds1307-2.1.25.dist-info/licenses/LICENSE
adafruit_circuitpython_ds1307-2.1.25.dist-info/METADATA
adafruit_circuitpython_ds1307-2.1.25.dist-info/WHEEL
adafruit_circuitpython_ds1307-2.1.25.dist-info/top_level.txt
adafruit_circuitpython_ds1307-2.1.25.dist-info/RECORD
